[
  {"storename":"1xxxxxxxx","bankaccout":"12345678","routnum":"24325545","company":"杭州xxx有限公司"},
  {"storename":"2xxxxxxxx","bankaccout":"12345678","routnum":"24325545","company":"杭州xxx有限公司"},
  {"storename":"3xxxxxxxx","bankaccout":"12345678","routnum":"24325545","company":"杭州xxx有限公司"},
  {"storename":"4xxxxxxxx","bankaccout":"12345678","routnum":"24325545","company":"杭州xxx有限公司"},
  {"storename":"5xxxxxxxx","bankaccout":"12345678","routnum":"24325545","company":"杭州xxx有限公司"},
  {"storename":"6xxxxxxxx","bankaccout":"12345678","routnum":"24325545","company":"杭州xxx有限公司"},
  {"storename":"7xxxxxxxx","bankaccout":"12345678","routnum":"24325545","company":"杭州xxx有限公司"}
  ]